unzipxz.py
unzipxz-0.0.1.dist-info/LICENSE
unzipxz-0.0.1.dist-info/METADATA
unzipxz-0.0.1.dist-info/WHEEL
unzipxz-0.0.1.dist-info/top_level.txt
unzipxz-0.0.1.dist-info/RECORD
