Metadata-Version: 2.1
Name: unzipxz
Version: 0.0.1
Summary: uwu requests www
Author: ayamessh
Project-URL: Homepage, https://discord.com/oppz
Project-URL: Issues, https://discord.com/oppz
Classifier: Programming Language :: Python :: 3
Classifier: License :: OSI Approved :: MIT License
Classifier: Operating System :: OS Independent
Requires-Python: >=3.9
License-File: LICENSE
